bakara/__init__.py
bakara/__main__.py
bakara-0.0.1.data/scripts/bakara
bakara-0.0.1.dist-info/LICENSE
bakara-0.0.1.dist-info/METADATA
bakara-0.0.1.dist-info/WHEEL
bakara-0.0.1.dist-info/top_level.txt
bakara-0.0.1.dist-info/RECORD
