Metadata-Version: 2.1
Name: bakara
Version: 0.0.1
Summary: Bakara
Home-page: https://github.com/salosh/bakara.git
Author: Salo Shp
Author-email: support@salosh.org
License: GPLv3
Platform: UNKNOWN
Classifier: Environment :: Console
Classifier: Intended Audience :: System Administrators
Classifier: Programming Language :: Python
Classifier: Topic :: System :: Distributed Computing
Classifier: License :: OSI Approved :: GNU General Public License v3 or later (GPLv3+)
Classifier: Natural Language :: English
Classifier: Operating System :: OS Independent
